PiKit/__init__.py
PiKit/add_num.py
PiKit/cvkit.py
PiKit/face_detetion.py
PiKit-1.0.12.dist-info/METADATA
PiKit-1.0.12.dist-info/WHEEL
PiKit-1.0.12.dist-info/top_level.txt
PiKit-1.0.12.dist-info/RECORD
